.gitignore
MANIFEST.in
README.md
celerywatch-init.d
setup.py
celerywatch/__init__.py
celerywatch/daemon.py
celerywatch/watcher.py
celerywatch.egg-info/PKG-INFO
celerywatch.egg-info/SOURCES.txt
celerywatch.egg-info/dependency_links.txt
celerywatch.egg-info/not-zip-safe
celerywatch.egg-info/requires.txt
celerywatch.egg-info/top_level.txt
celerywatch/bin/stopCeleryd.sh
celerywatch/management/__init__.py
celerywatch/management/commands/__init__.py
celerywatch/management/commands/celeryd_watch.py