Metadata-Version: 1.0
Name: celerywatch
Version: 0.1.1
Summary: Runs a celery app that monitors celeryd and stops it if it fails too many tasks.
Home-page: http://pypi.python.org/pypi/celerywatch/
Author: Matt Long
Author-email: matt@mattlong.org
License: BSD
Platform: UNKNOWN
Classifier: Programming Language :: Python
Classifier: Programming Language :: Python :: 2
Classifier: License :: OSI Approved :: MIT License
Classifier: Operating System :: Unix
Classifier: Development Status :: 3 - Alpha
Classifier: Intended Audience :: Developers
Classifier: Intended Audience :: System Administrators
Classifier: Topic :: Internet :: WWW/HTTP
Classifier: Topic :: Software Development :: Libraries :: Python Modules
